performance_evaluation_tool/__init__.py
performance_evaluation_tool/config/quotient_mapping.json
performance_evaluation_tool/run.py
performance_evaluation_tool/src/__init__.py
performance_evaluation_tool/src/performance_evaluation.py
performance_evaluation_tool/test/__init__.py
performance_evaluation_tool/test/performance_evaluation_test.py
performance_evaluation_tool/test/recall_distance_function_test.py
performance_evaluation_tool/test/test_image_folder/test1/image.png
performance_evaluation_tool/test/test_image_folder/test2/image.png
performance_evaluation_tool/test/test_image_folder/test3/image.png
performance_evaluation_tool/test/test_image_folder/test4/image.png
performance_evaluation_tool-0.1.6.dist-info/METADATA
performance_evaluation_tool-0.1.6.dist-info/WHEEL
performance_evaluation_tool-0.1.6.dist-info/RECORD
