Metadata-Version: 2.1
Name: performance-evaluation-tool
Version: 0.1.6
Summary: Performance Evaluation for Perception Pipeline
Author: umandavia
Author-email: umandavia@forterra.com
Requires-Python: >=3.8,<4.0
Classifier: Programming Language :: Python :: 3
Classifier: Programming Language :: Python :: 3.8
Classifier: Programming Language :: Python :: 3.9
Classifier: Programming Language :: Python :: 3.10
Classifier: Programming Language :: Python :: 3.11
Classifier: Programming Language :: Python :: 3.12
Requires-Dist: numpy (>=1.24.3,<2.0.0)
Requires-Dist: opencv-python (>=4.7.0.72,<5.0.0.0)
Requires-Dist: scikit-learn (>=1.2.2,<2.0.0)
